ragraph/__init__.py
ragraph/edge.py
ragraph/generic.py
ragraph/graph.py
ragraph/node.py
ragraph/utils.py
ragraph/analysis/__init__.py
ragraph/analysis/_classes.py
ragraph/analysis/_utils.py
ragraph/analysis/bus/__init__.py
ragraph/analysis/bus/_gamma.py
ragraph/analysis/cluster/__init__.py
ragraph/analysis/cluster/_markov.py
ragraph/analysis/cluster/_tarjan.py
ragraph/analysis/comparison/__init__.py
ragraph/analysis/comparison/_delta.py
ragraph/analysis/comparison/_sigma.py
ragraph/analysis/comparison/utils.py
ragraph/analysis/compatibility/__init__.py
ragraph/analysis/compatibility/bdd.py
ragraph/analysis/heuristics/__init__.py
ragraph/analysis/heuristics/_johnson.py
ragraph/analysis/heuristics/_markov_gamma.py
ragraph/analysis/sequence/__init__.py
ragraph/analysis/sequence/_axis.py
ragraph/analysis/sequence/_genetic.py
ragraph/analysis/sequence/_markov.py
ragraph/analysis/sequence/_name.py
ragraph/analysis/sequence/_scc_tearing.py
ragraph/analysis/sequence/_tarjan.py
ragraph/analysis/sequence/metrics.py
ragraph/analysis/sequence/utils.py
ragraph/analysis/similarity/__init__.py
ragraph/analysis/similarity/_jaccard.py
ragraph/analysis/similarity/_similarity.py
ragraph/analysis/similarity/utils.py
ragraph/colors/__init__.py
ragraph/colors/cubehelix.py
ragraph/colors/utils.py
ragraph/datasets/__init__.py
ragraph/datasets/aircraft_engine/__init__.py
ragraph/datasets/aircraft_engine/aircraft_engine_edges.csv
ragraph/datasets/aircraft_engine/aircraft_engine_nodes.csv
ragraph/datasets/architecture_integral/__init__.py
ragraph/datasets/architecture_integral/architecture_integral_edges.csv
ragraph/datasets/architecture_integral/architecture_integral_nodes.csv
ragraph/datasets/architecture_mix/__init__.py
ragraph/datasets/architecture_mix/architecture_mix_edges.csv
ragraph/datasets/architecture_mix/architecture_mix_nodes.csv
ragraph/datasets/architecture_modular/__init__.py
ragraph/datasets/architecture_modular/architecture_modular_edges.csv
ragraph-1.23.2.dist-info/METADATA
ragraph-1.23.2.dist-info/WHEEL
ragraph-1.23.2.dist-info/licenses/LICENSE.md
ragraph-1.23.2.dist-info/RECORD
