Metadata-Version: 2.4
Name: ragraph
Version: 1.23.2
Summary: Ratio graph handling in Python.
Project-URL: Homepage, https://ragraph.ratio-case.nl
Project-URL: Repository, https://gitlab.com/ratio-case-os/python/ragraph
Project-URL: Bug Tracker, https://gitlab.com/ratio-case-os/python/ragraph/-/issues
Project-URL: Changelog, https://ragraph.ratio-case.nl/CHANGELOG/
Author-email: "Ratio Innovations B.V." <info@ratio-case.nl>
License-Expression: GPL-3.0-or-later
License-File: LICENSE.md
Keywords: analysis,graph,network,visualization
Requires-Python: >=3.11
Requires-Dist: dd>=0.6.0
Requires-Dist: lxml>=6.0.2
Requires-Dist: numpy>=2.3.5
Requires-Dist: ratio-genetic-py>=0.4.0
Requires-Dist: ruamel-yaml>=0.18.16
Requires-Dist: strenum>=0.4.15
Provides-Extra: all
Requires-Dist: plotly[kaleido]>=6.5.0; extra == 'all'
Requires-Dist: rachord>=0.2.0; extra == 'all'
Requires-Dist: raesl; extra == 'all'
Provides-Extra: esl
Requires-Dist: raesl; extra == 'esl'
Provides-Extra: plot
Requires-Dist: plotly[kaleido]>=6.5.0; extra == 'plot'
Requires-Dist: rachord>=0.2.0; extra == 'plot'
